schnitsum/__init__.py
schnitsum/bin/summarize.py
schnitsum/main.py
schnitsum-0.4.10.dist-info/entry_points.txt
schnitsum-0.4.10.dist-info/LICENSE
schnitsum-0.4.10.dist-info/WHEEL
schnitsum-0.4.10.dist-info/METADATA
schnitsum-0.4.10.dist-info/RECORD
