Metadata-Version: 2.1
Name: schnitsum
Version: 0.4.10
Summary: 
Author: sobamchan
Author-email: oh.sore.sore.soutarou@gmail.com
Requires-Python: >=3.9,<4.0
Classifier: Programming Language :: Python :: 3
Classifier: Programming Language :: Python :: 3.9
Classifier: Programming Language :: Python :: 3.10
Classifier: Programming Language :: Python :: 3.11
Requires-Dist: fire (>=0.4.0,<0.5.0)
Requires-Dist: sienna (>=0.2.0)
Requires-Dist: torch (>=2.0.0)
Requires-Dist: transformers (>=4.33.2,<5.0.0)
